pcTools543/__init__.py
pcTools543/pcTools.py
pcTools543-0.11.dist-info/LICENSE
pcTools543-0.11.dist-info/METADATA
pcTools543-0.11.dist-info/WHEEL
pcTools543-0.11.dist-info/entry_points.txt
pcTools543-0.11.dist-info/top_level.txt
pcTools543-0.11.dist-info/RECORD
