Metadata-Version: 2.1
Name: pcTools543
Version: 0.11
Summary: Just
Home-page: https://github.com/
Author: Su
Author-email: aaaaaaaa@qq.com
License: UNKNOWN
Platform: UNKNOWN
Classifier: Programming Language :: Python :: 3
Classifier: License :: OSI Approved :: MIT License
Classifier: Operating System :: OS Independent
License-File: LICENSE
